biobear-0.23.7.dist-info/METADATA
biobear-0.23.7.dist-info/WHEEL
biobear-0.23.7.dist-info/licenses/LICENSE
biobear/py.typed
biobear/biobear.pyi
biobear/reader.py
biobear/__init__.py
biobear/compression.py
biobear/biobear.cpython-312-aarch64-linux-gnu.so
biobear-0.23.7.dist-info/RECORD
