Metadata-Version: 2.4
Name: biobear
Version: 0.23.7
Classifier: Programming Language :: Rust
Classifier: Programming Language :: Python :: Implementation :: CPython
Classifier: Programming Language :: Python :: Implementation :: PyPy
Requires-Dist: pyarrow >=15
License-File: LICENSE
Summary: A package for working with Bioinformatics data with SQL and Arrow
Author-email: WHERE TRUE devs <thauck+biobear@wheretrue.com>
Requires-Python: >=3.9
